ati_autogpt/__init__.py
ati_autogpt/instrumentor.py
ati_integrations_autogpt-0.1.1.dist-info/METADATA
ati_integrations_autogpt-0.1.1.dist-info/WHEEL
ati_integrations_autogpt-0.1.1.dist-info/RECORD
