Metadata-Version: 2.4
Name: ati-integrations-autogpt
Version: 0.1.1
Summary: ATI Integration for AutoGPT
Project-URL: Homepage, https://iocane.ai
Project-URL: Repository, https://github.com/iocane-ai/ati-integrations
Author-email: IOcane ATI Team <support@iocane.ai>
Classifier: Programming Language :: Python
Classifier: Programming Language :: Python :: 3.10
Classifier: Programming Language :: Python :: 3.11
Classifier: Programming Language :: Python :: 3.12
Classifier: Typing :: Typed
Requires-Python: >=3.10
Requires-Dist: ati-sdk==0.1.0
